blisswebui/__init__.py
blisswebui/static/favicon.ico
blisswebui/static/index.html
blisswebui/static/assets/bliss-a0afec9e.svg
blisswebui/static/assets/fa-brands-400-808443ae.ttf
blisswebui/static/assets/fa-brands-400-d7236a19.woff2
blisswebui/static/assets/fa-regular-400-54cf6086.ttf
blisswebui/static/assets/fa-regular-400-e3456d12.woff2
blisswebui/static/assets/fa-solid-900-aa759986.woff2
blisswebui/static/assets/fa-solid-900-d2f05935.ttf
blisswebui/static/assets/fa-v4compatibility-0ce9033c.woff2
blisswebui/static/assets/fa-v4compatibility-30f6abf6.ttf
blisswebui/static/assets/fontawesomemore-webfont-6020ee57.woff2
blisswebui/static/assets/index-86bc972c.js
blisswebui/static/assets/index-b1fdb837.css
blisswebui/static/assets/pxiEyp8kv8JHgFVrJJbecnFHGPezSQ-0cd83f4b.woff2
blisswebui/static/assets/pxiEyp8kv8JHgFVrJJfecnFHGPc-fab32cce.woff2
blisswebui/static/assets/pxiEyp8kv8JHgFVrJJnecnFHGPezSQ-5d28e623.woff2
blisswebui-2025.6.0.dist-info/METADATA
blisswebui-2025.6.0.dist-info/WHEEL
blisswebui-2025.6.0.dist-info/top_level.txt
blisswebui-2025.6.0.dist-info/RECORD
