Metadata-Version: 2.4
Name: blisswebui
Version: 2025.6.0
Summary: Web User Interface for BLISS
Author-email: ESRF <bcu@esrf.fr>
Project-URL: Repository, https://gitlab.esrf.fr/bliss/blisswebui
Classifier: Intended Audience :: Science/Research
Classifier: License :: OSI Approved :: MIT License
Classifier: Programming Language :: Python :: 3
Requires-Python: >=3.8
